{
  "collectionName": "components_content_heading_description_images",
  "info": {
    "displayName": "heading_description_image",
    "icon": "archive",
    "description": ""
  },
  "options": {},
  "attributes": {
    "heading": {
      "type": "string",
      "required": true
    },
    "description": {
      "type": "text",
      "required": true
    },
    "image": {
      "type": "media",
      "multiple": false,
      "required": false,
      "allowedTypes": [
        "images"
      ]
    }
  }
}
